sqlclz/__init__.py
sqlclz/__main__.py
sqlclz/annotation.py
sqlclz/cli.py
sqlclz/connection.py
sqlclz/diagram.py
sqlclz/dot.py
sqlclz/expr.py
sqlclz/func.py
sqlclz/func_date.py
sqlclz/func_dec.py
sqlclz/func_stat.py
sqlclz/func_win.py
sqlclz/literal.py
sqlclz/rich.py
sqlclz/stat.py
sqlclz/stat_start.py
sqlclz/table.py
sqlclz/table_nt.py
sqlclz/util.py
sqlclz-1.0.0.dist-info/licenses/LICENSE
sqlclz-1.0.0.dist-info/METADATA
sqlclz-1.0.0.dist-info/WHEEL
sqlclz-1.0.0.dist-info/top_level.txt
sqlclz-1.0.0.dist-info/RECORD
