Metadata-Version: 2.4
Name: sqlclz
Version: 1.0.0
Summary: Python functions to build a SQL (sqlite3) statement
Author-email: Yu-Ting Wei <ytsimon2004@gmail.com>, Ta-Shun Su <antoniost29@gmail.com>
License: BSD 3-Clause License
Project-URL: Homepage, https://github.com/ytsimon2004/sqlclz
Project-URL: Repository, https://github.com/ytsimon2004/sqlclz
Project-URL: Issues, https://github.com/ytsimon2004/sqlclz/issues
Keywords: sql
Classifier: Development Status :: 3 - Alpha
Classifier: Programming Language :: Python :: 3.10
Classifier: Programming Language :: Python :: 3.11
Classifier: Programming Language :: Python :: 3.12
Classifier: License :: OSI Approved :: BSD License
Classifier: Natural Language :: English
Classifier: Operating System :: OS Independent
Classifier: Topic :: Utilities
Classifier: Intended Audience :: Developers
Classifier: Typing :: Typed
Requires-Python: >=3.10
License-File: LICENSE
Requires-Dist: polars
Requires-Dist: pandas
Requires-Dist: argclz
Requires-Dist: rich
Provides-Extra: opt
Requires-Dist: diagram; extra == "opt"
Dynamic: license-file
